dgen/__init__.py
dgen/cli.py
dgen/jinja.py
dgen/settings.py
dgen/tempdir.py
dgen/commands/__init__.py
dgen/commands/model/__init__.py
dgen/commands/model/command.py
dgen/commands/model/templates/model.py
dgen/commands/templates/__init__.py
dgen/commands/templates/command.py
dgen/commands/templates/templates/base.html
dgen/commands/templates/templates/breadcrumb.html
dgen/commands/templates/templates/confirm_delete.html
dgen/commands/templates/templates/form.html
dgen/commands/templates/templates/index.html
dgen/commands/templates/templates/list.html
dgen/validators/__init__.py
dgen/validators/model.py
dgen-0.2.1.dist-info/METADATA
dgen-0.2.1.dist-info/RECORD
dgen-0.2.1.dist-info/WHEEL
dgen-0.2.1.dist-info/entry_points.txt
dgen-0.2.1.dist-info/top_level.txt
