Metadata-Version: 2.1
Name: dgen
Version: 0.2.1
Summary: Command-line utility for Django code generation.
Home-page: https://github.com/dominem/dgen
Author: Dominik Magdaleński
Author-email: dominik.magdalenski@gmail.com
License: MIT
Platform: any
Classifier: Development Status :: 4 - Beta
Classifier: Environment :: Console
Classifier: Intended Audience :: Developers
Classifier: License :: OSI Approved :: MIT License
Classifier: Operating System :: OS Independent
Classifier: Programming Language :: Python
Classifier: Programming Language :: Python :: 3
Classifier: Topic :: Software Development :: Libraries :: Python Modules
Requires-Dist: click
Requires-Dist: Jinja2
